Workbook

Sheet Sales
A1: Date | B1: Invoice No. | C1: Customer | D1: Product | E1: Quantity | F1: Unit Price | G1: Total Sales | H1: Payment Type | I1: Amount Received | J1: Outstanding
A2: 46266 | B2: INV-001 | C2: Al-Rehman Traders | D2: Keyboard | E2: 10 | F2: 1800 | G2: =E2*F2 -> 18000 | H2: Cash | I2: =G2 -> 18000 | J2: =G2-I2 -> 0
A3: 46266 | B3: INV-002 | C3: City Computers | D3: Mouse | E3: 15 | F3: 900 | G3: =E3*F3 -> 13500 | H3: Cash | I3: =G3 -> 13500 | J3: =G3-I3 -> 0
A4: 46267 | B4: INV-003 | C4: Bright Star Electronics | D4: Headphones | E4: 8 | F4: 2500 | G4: =E4*F4 -> 20000 | H4: Credit | I4: 10000 | J4: =G4-I4 -> 10000
A5: 46267 | B5: INV-004 | C5: Prime Tech Store | D5: Webcam | E5: 5 | F5: 3200 | G5: =E5*F5 -> 16000 | H5: Cash | I5: =G5 -> 16000 | J5: =G5-I5 -> 0
A6: 46268 | B6: INV-005 | C6: Digital Hub | D6: USB Drive | E6: 20 | F6: 750 | G6: =E6*F6 -> 15000 | H6: Credit | I6: 0 | J6: =G6-I6 -> 15000
A7: 46268 | B7: INV-006 | C7: Osama Traders | D7: Power Bank | E7: 6 | F7: 2800 | G7: =E7*F7 -> 16800 | H7: Cash | I7: =G7 -> 16800 | J7: =G7-I7 -> 0
A8: 46269 | B8: INV-007 | C8: Speedy Gadgets | D8: Keyboard | E8: 12 | F8: 1800 | G8: =E8*F8 -> 21600 | H8: Credit | I8: 10000 | J8: =G8-I8 -> 11600
A9: 46269 | B9: INV-008 | C9: National Computer Center | D9: Mouse | E9: 10 | F9: 900 | G9: =E9*F9 -> 9000 | H9: Cash | I9: =G9 -> 9000 | J9: =G9-I9 -> 0
A10: 46270 | B10: INV-009 | C10: Sunrise Electronics | D10: Headphones | E10: 4 | F10: 2500 | G10: =E10*F10 -> 10000 | H10: Cash | I10: =G10 -> 10000 | J10: =G10-I10 -> 0
A11: 46270 | B11: INV-010 | C11: Metro Traders | D11: Webcam | E11: 7 | F11: 3200 | G11: =E11*F11 -> 22400 | H11: Credit | I11: 0 | J11: =G11-I11 -> 22400
A12: 46273 | B12: INV-011 | C12: Value Mart Electronics | D12: USB Drive | E12: 25 | F12: 750 | G12: =E12*F12 -> 18750 | H12: Cash | I12: =G12 -> 18750 | J12: =G12-I12 -> 0
A13: 46273 | B13: INV-012 | C13: Falcon IT Solutions | D13: Power Bank | E13: 8 | F13: 2800 | G13: =E13*F13 -> 22400 | H13: Credit | I13: 12000 | J13: =G13-I13 -> 10400
A14: 46274 | B14: INV-013 | C14: Al-Rehman Traders | D14: Mouse | E14: 18 | F14: 900 | G14: =E14*F14 -> 16200 | H14: Cash | I14: =G14 -> 16200 | J14: =G14-I14 -> 0
A15: 46274 | B15: INV-014 | C15: City Computers | D15: Keyboard | E15: 9 | F15: 1800 | G15: =E15*F15 -> 16200 | H15: Credit | I15: 0 | J15: =G15-I15 -> 16200
A16: 46275 | B16: INV-015 | C16: Bright Star Electronics | D16: Webcam | E16: 6 | F16: 3200 | G16: =E16*F16 -> 19200 | H16: Cash | I16: =G16 -> 19200 | J16: =G16-I16 -> 0
A17: 46275 | B17: INV-016 | C17: Prime Tech Store | D17: Headphones | E17: 10 | F17: 2500 | G17: =E17*F17 -> 25000 | H17: Credit | I17: 15000 | J17: =G17-I17 -> 10000
A18: 46276 | B18: INV-017 | C18: Digital Hub | D18: Power Bank | E18: 5 | F18: 2800 | G18: =E18*F18 -> 14000 | H18: Cash | I18: =G18 -> 14000 | J18: =G18-I18 -> 0
A19: 46276 | B19: INV-018 | C19: Osama Traders | D19: USB Drive | E19: 30 | F19: 750 | G19: =E19*F19 -> 22500 | H19: Cash | I19: =G19 -> 22500 | J19: =G19-I19 -> 0
A20: 46277 | B20: INV-019 | C20: Speedy Gadgets | D20: Mouse | E20: 12 | F20: 900 | G20: =E20*F20 -> 10800 | H20: Credit | I20: 0 | J20: =G20-I20 -> 10800
A21: 46279 | B21: INV-020 | C21: National Computer Center | D21: Headphones | E21: 6 | F21: 2500 | G21: =E21*F21 -> 15000 | H21: Cash | I21: =G21 -> 15000 | J21: =G21-I21 -> 0
A22: 46280 | B22: INV-021 | C22: Sunrise Electronics | D22: Keyboard | E22: 14 | F22: 1800 | G22: =E22*F22 -> 25200 | H22: Credit | I22: 10000 | J22: =G22-I22 -> 15200
A23: 46281 | B23: INV-022 | C23: Metro Traders | D23: Webcam | E23: 4 | F23: 3200 | G23: =E23*F23 -> 12800 | H23: Cash | I23: =G23 -> 12800 | J23: =G23-I23 -> 0
A24: 46282 | B24: INV-023 | C24: Value Mart Electronics | D24: Power Bank | E24: 9 | F24: 2800 | G24: =E24*F24 -> 25200 | H24: Credit | I24: 0 | J24: =G24-I24 -> 25200
A25: 46283 | B25: INV-024 | C25: Falcon IT Solutions | D25: USB Drive | E25: 22 | F25: 750 | G25: =E25*F25 -> 16500 | H25: Cash | I25: =G25 -> 16500 | J25: =G25-I25 -> 0
A26: 46286 | B26: INV-025 | C26: Al-Rehman Traders | D26: Headphones | E26: 7 | F26: 2500 | G26: =E26*F26 -> 17500 | H26: Cash | I26: =G26 -> 17500 | J26: =G26-I26 -> 0
A27: 46288 | B27: INV-026 | C27: City Computers | D27: Mouse | E27: 16 | F27: 900 | G27: =E27*F27 -> 14400 | H27: Credit | I27: 8000 | J27: =G27-I27 -> 6400
A28: 46290 | B28: INV-027 | C28: Bright Star Electronics | D28: Keyboard | E28: 11 | F28: 1800 | G28: =E28*F28 -> 19800 | H28: Cash | I28: =G28 -> 19800 | J28: =G28-I28 -> 0
A29: 46293 | B29: INV-028 | C29: Prime Tech Store | D29: Power Bank | E29: 7 | F29: 2800 | G29: =E29*F29 -> 19600 | H29: Credit | I29: 0 | J29: =G29-I29 -> 19600
F30: TOTAL | G30: =SUM(G2:G29) -> 493350 | I30: =SUM(I2:I29) -> 320550 | J30: =SUM(J2:J29) -> 172800

Sheet Purchases
A1: Date | B1: Purchase No. | C1: Supplier | D1: Product | E1: Quantity | F1: Unit Cost | G1: Total Purchase | H1: Payment Type | I1: Amount Paid | J1: Outstanding
A2: 46266 | B2: PUR-001 | C2: Al-Fateh Electronics Wholesale | D2: Keyboard | E2: 40 | F2: 1300 | G2: =E2*F2 -> 52000 | H2: Cash | I2: =G2 -> 52000 | J2: =G2-I2 -> 0
A3: 46267 | B3: PUR-002 | C3: Karachi Tech Supplies | D3: Mouse | E3: 60 | F3: 650 | G3: =E3*F3 -> 39000 | H3: Credit | I3: 15000 | J3: =G3-I3 -> 24000
A4: 46268 | B4: PUR-003 | C4: Lahore Gadget Importers | D4: Headphones | E4: 30 | F4: 1800 | G4: =E4*F4 -> 54000 | H4: Cash | I4: =G4 -> 54000 | J4: =G4-I4 -> 0
A5: 46270 | B5: PUR-004 | C5: Prime Distributors Ltd | D5: Webcam | E5: 20 | F5: 2300 | G5: =E5*F5 -> 46000 | H5: Credit | I5: 0 | J5: =G5-I5 -> 46000
A6: 46271 | B6: PUR-005 | C6: National Electronics Wholesale | D6: USB Drive | E6: 100 | F6: 500 | G6: =E6*F6 -> 50000 | H6: Cash | I6: =G6 -> 50000 | J6: =G6-I6 -> 0
A7: 46273 | B7: PUR-006 | C7: Al-Fateh Electronics Wholesale | D7: Power Bank | E7: 25 | F7: 2000 | G7: =E7*F7 -> 50000 | H7: Credit | I7: 20000 | J7: =G7-I7 -> 30000
A8: 46276 | B8: PUR-007 | C8: Karachi Tech Supplies | D8: Keyboard | E8: 20 | F8: 1300 | G8: =E8*F8 -> 26000 | H8: Cash | I8: =G8 -> 26000 | J8: =G8-I8 -> 0
A9: 46279 | B9: PUR-008 | C9: Lahore Gadget Importers | D9: Mouse | E9: 35 | F9: 650 | G9: =E9*F9 -> 22750 | H9: Credit | I9: 0 | J9: =G9-I9 -> 22750
A10: 46282 | B10: PUR-009 | C10: Prime Distributors Ltd | D10: Headphones | E10: 15 | F10: 1800 | G10: =E10*F10 -> 27000 | H10: Cash | I10: =G10 -> 27000 | J10: =G10-I10 -> 0
A11: 46285 | B11: PUR-010 | C11: National Electronics Wholesale | D11: Webcam | E11: 12 | F11: 2300 | G11: =E11*F11 -> 27600 | H11: Credit | I11: 10000 | J11: =G11-I11 -> 17600
A12: 46289 | B12: PUR-011 | C12: Al-Fateh Electronics Wholesale | D12: Power Bank | E12: 15 | F12: 2000 | G12: =E12*F12 -> 30000 | H12: Cash | I12: =G12 -> 30000 | J12: =G12-I12 -> 0
F13: TOTAL | G13: =SUM(G2:G12) -> 424350 | I13: =SUM(I2:I12) -> 284000 | J13: =SUM(J2:J12) -> 140350

Sheet Expenses
A1: Date | B1: Expense Category | C1: Description | D1: Payment Method | E1: Amount
A2: 46266 | B2: Rent | C2: Shop rent for September | D2: Bank Transfer | E2: 35000
A3: 46268 | B3: Electricity | C3: Electricity bill - August usage | D3: Cash | E3: 7000
A4: 46269 | B4: Internet | C4: Monthly internet package | D4: Bank Transfer | E4: 4500
A5: 46271 | B5: Transportation | C5: Delivery van fuel | D5: Cash | E5: 3200
A6: 46273 | B6: Office Supplies | C6: Stationery and invoice books | D6: Cash | E6: 2200
A7: 46275 | B7: Telephone | C7: Mobile & office phone bill | D7: Cash | E7: 1800
A8: 46277 | B8: Delivery | C8: Courier charges for customer orders | D8: Cash | E8: 2800
A9: 46280 | B9: Bank Charges | C9: Bank account service charges | D9: Bank Transfer | E9: 600
A10: 46283 | B10: Transportation | C10: Fuel for supplier pickup | D10: Cash | E10: 2500
A11: 46287 | B11: Delivery | C11: Courier charges - bulk order | D11: Cash | E11: 3500
A12: 46292 | B12: Office Supplies | C12: Printer ink and paper | D12: Cash | E12: 1700
D13: TOTAL | E13: =SUM(E2:E12) -> 64800

Sheet Summary
A1: TechBridge Distributors — Monthly Sales & Expense Summary
A2: Accounting Period: September 2026 | Currency: PKR | Fictional company for portfolio/learning purposes
A4: 1. KEY TOTALS | F4: Sales by Product
A5: Total Sales | B5: =SUM(Sales!G2:G29) -> 493350 | F5: Product | G5: Total Sales (PKR)
A6: Total Purchases | B6: =SUM(Purchases!G2:G12) -> 424350 | F6: Keyboard | G6: =SUMIF(Sales!$D$2:$D$29,F6,Sales!$G$2:$G$29) -> 100800
A7: Total Expenses | B7: =SUM(Expenses!E2:E12) -> 64800 | F7: Mouse | G7: =SUMIF(Sales!$D$2:$D$29,F7,Sales!$G$2:$G$29) -> 63900
A8: Total Amount Received (from customers) | B8: =SUM(Sales!I2:I29) -> 320550 | F8: Headphones | G8: =SUMIF(Sales!$D$2:$D$29,F8,Sales!$G$2:$G$29) -> 87500
A9: Total Amount Paid (to suppliers) | B9: =SUM(Purchases!I2:I12) -> 284000 | F9: Webcam | G9: =SUMIF(Sales!$D$2:$D$29,F9,Sales!$G$2:$G$29) -> 70400
F10: USB Drive | G10: =SUMIF(Sales!$D$2:$D$29,F10,Sales!$G$2:$G$29) -> 72750
A11: 2. RECEIVABLES & PAYABLES | F11: Power Bank | G11: =SUMIF(Sales!$D$2:$D$29,F11,Sales!$G$2:$G$29) -> 98000
A12: Accounts Receivable (owed by customers) | B12: =SUM(Sales!J2:J29) -> 172800
A13: Accounts Payable (owed to suppliers) | B13: =SUM(Purchases!J2:J12) -> 140350 | F13: Expenses by Category
A14: Customer Collection Status | B14: =IF(B12>0,"Balance still outstanding from customers","All customer invoices fully collected") -> Balance still outstanding from customers | F14: Category | G14: Total Amount (PKR)
A15: Supplier Payment Status | B15: =IF(B13>0,"Balance still owed to suppliers","All supplier bills fully paid") -> Balance still owed to suppliers | F15: Rent | G15: =SUMIF(Expenses!$B$2:$B$12,F15,Expenses!$E$2:$E$12) -> 35000
F16: Electricity | G16: =SUMIF(Expenses!$B$2:$B$12,F16,Expenses!$E$2:$E$12) -> 7000
A17: 3. PROFITABILITY | F17: Internet | G17: =SUMIF(Expenses!$B$2:$B$12,F17,Expenses!$E$2:$E$12) -> 4500
A18: Estimated Gross Profit (Total Sales − Total Purchases) | B18: =B5-B6 -> 69000 | F18: Transportation | G18: =SUMIF(Expenses!$B$2:$B$12,F18,Expenses!$E$2:$E$12) -> 5700
A19: Net Profit (Gross Profit − Total Expenses) | B19: =B18-B7 -> 4200 | F19: Office Supplies | G19: =SUMIF(Expenses!$B$2:$B$12,F19,Expenses!$E$2:$E$12) -> 3900
A20: Note: Gross Profit here is estimated as Total Sales minus Total Purchases for the month, since this beginner-level project does not track opening/closing inventory. A full accounting system would use Cost of Goods Sold instead of total purchases. | F20: Telephone | G20: =SUMIF(Expenses!$B$2:$B$12,F20,Expenses!$E$2:$E$12) -> 1800
F21: Delivery | G21: =SUMIF(Expenses!$B$2:$B$12,F21,Expenses!$E$2:$E$12) -> 6300
A22: 4. INVOICE ACTIVITY | F22: Bank Charges | G22: =SUMIF(Expenses!$B$2:$B$12,F22,Expenses!$E$2:$E$12) -> 600
A23: Number of Cash Sales Invoices | B23: =COUNTIF(Sales!H2:H29,"Cash") -> 16
A24: Number of Credit Sales Invoices | B24: =COUNTIF(Sales!H2:H29,"Credit") -> 12
A25: Number of Cash Purchases | B25: =COUNTIF(Purchases!H2:H12,"Cash") -> 6
A26: Number of Credit Purchases | B26: =COUNTIF(Purchases!H2:H12,"Credit") -> 5
